tree_sitter_sql_bigquery/__init__.py
tree_sitter_sql_bigquery/__init__.pyi
tree_sitter_sql_bigquery/_binding.pyd
tree_sitter_sql_bigquery/binding.c
tree_sitter_sql_bigquery/py.typed
tree_sitter_sql_bigquery/queries/highlights.scm
tree_sitter_sql_bigquery-0.8.0.dist-info/LICENSE
tree_sitter_sql_bigquery-0.8.0.dist-info/METADATA
tree_sitter_sql_bigquery-0.8.0.dist-info/WHEEL
tree_sitter_sql_bigquery-0.8.0.dist-info/top_level.txt
tree_sitter_sql_bigquery-0.8.0.dist-info/RECORD
